drops/__init__.py
drops/admin.py
drops/apps.py
drops/models.py
drops/management/__init__.py
drops/management/commands/__init__.py
drops/management/commands/chain.py
drops/management/commands/create_admin.py
drops/management/commands/uptime.py
drops/serializers/__init__.py
drops/serializers/json.py
drops/settings/__init__.py
drops/settings/components.py
drops/settings/settings.py
drops/settings/utils.py
django_drops-1.0.0b6.dist-info/METADATA
django_drops-1.0.0b6.dist-info/WHEEL
django_drops-1.0.0b6.dist-info/top_level.txt
django_drops-1.0.0b6.dist-info/RECORD
