Metadata-Version: 2.4
Name: django-drops
Version: 1.0.0b6
Summary: Various helpers for django-based projects
Author-email: Abdrakhmanov Vladimir <369565@gmail.com>, Chechetkin Ilya <illaech@gmail.com>
Maintainer-email: Abdrakhmanov Vladimir <369565@gmail.com>, Chechetkin Ilya <illaech@gmail.com>, Golubev Alexey <dr.freecx@gmail.com>
License: MIT
Classifier: Development Status :: 4 - Beta
Classifier: Framework :: Django
Classifier: Framework :: Django :: 5.2
Classifier: Framework :: Django :: 6
Classifier: Framework :: Django :: 6.0
Classifier: Intended Audience :: Developers
Classifier: Programming Language :: Python
Classifier: Programming Language :: Python :: 3
Classifier: Programming Language :: Python :: 3.12
Classifier: Typing :: Typed
Requires-Python: >=3.12
Requires-Dist: dj-database-url>=3.0.1
Requires-Dist: django>=5.2
Requires-Dist: pydantic>=2.12.5
Requires-Dist: pydantic-settings>=2.12.0
